semplex_cli/__init__.py
semplex_cli/__main__.py
semplex_cli/chunker.py
semplex_cli/cli.py
semplex_cli/types.py
semplex_cli/watcher.py
semplex_cli/commands/__init__.py
semplex_cli/commands/auth.py
semplex_cli/commands/config.py
semplex_cli/commands/watch.py
semplex_cli/extractors/__init__.py
semplex_cli/extractors/code_extractor.py
semplex_cli/extractors/csv_extractor.py
semplex_cli/extractors/docx_extractor.py
semplex_cli/extractors/excel_extractor.py
semplex_cli/extractors/header_detector.py
semplex_cli/extractors/pdf_extractor.py
semplex_cli/extractors/pptx_extractor.py
semplex_cli/extractors/text_extractor.py
semplex_cli/utils/__init__.py
semplex_cli/utils/config.py
semplex_cli/utils/file_utils.py
semplex_cli/utils/process.py
semplex_cli/utils/state.py
semplex_cli-0.1.3.dist-info/METADATA
semplex_cli-0.1.3.dist-info/WHEEL
semplex_cli-0.1.3.dist-info/entry_points.txt
semplex_cli-0.1.3.dist-info/RECORD
