Metadata-Version: 2.4
Name: semplex-cli
Version: 0.1.3
Summary: CLI for Semplex platform - metadata tracking and curation
Project-URL: Homepage, https://semplex.simage.ai
Project-URL: Documentation, https://semplex.simage.ai/docs
Project-URL: Repository, https://github.com/simage-ai/semplex
Project-URL: Issues, https://github.com/simage-ai/semplex/issues
Author-email: Semplex Team <support@simage.ai>
License-Expression: MIT
Keywords: cli,data-management,file-watcher,metadata
Classifier: Development Status :: 3 - Alpha
Classifier: Intended Audience :: Developers
Classifier: Intended Audience :: Science/Research
Classifier: License :: OSI Approved :: MIT License
Classifier: Operating System :: OS Independent
Classifier: Programming Language :: Python :: 3
Classifier: Programming Language :: Python :: 3.11
Classifier: Programming Language :: Python :: 3.12
Classifier: Programming Language :: Python :: 3.13
Classifier: Topic :: Scientific/Engineering
Classifier: Topic :: System :: Filesystems
Requires-Python: >=3.11
Requires-Dist: httpx>=0.25.0
Requires-Dist: openpyxl>=3.1.0
Requires-Dist: pandas>=2.1.0
Requires-Dist: pathspec>=0.11.0
Requires-Dist: psutil>=5.9.0
Requires-Dist: pydantic-settings>=2.1.0
Requires-Dist: pydantic>=2.5.0
Requires-Dist: python-dotenv>=1.0.0
Requires-Dist: pyyaml>=6.0
Requires-Dist: rich>=13.7.0
Requires-Dist: typer[all]>=0.9.0
Requires-Dist: watchdog>=3.0.0
Provides-Extra: all
Requires-Dist: black>=23.0.0; extra == 'all'
Requires-Dist: mypy>=1.7.0; extra == 'all'
Requires-Dist: pypdf>=4.0.0; extra == 'all'
Requires-Dist: pytest-asyncio>=0.21.0; extra == 'all'
Requires-Dist: pytest-cov>=4.1.0; extra == 'all'
Requires-Dist: pytest>=7.4.0; extra == 'all'
Requires-Dist: python-docx>=1.1.0; extra == 'all'
Requires-Dist: python-pptx>=0.6.21; extra == 'all'
Requires-Dist: ruff>=0.1.0; extra == 'all'
Provides-Extra: dev
Requires-Dist: black>=23.0.0; extra == 'dev'
Requires-Dist: mypy>=1.7.0; extra == 'dev'
Requires-Dist: pytest-asyncio>=0.21.0; extra == 'dev'
Requires-Dist: pytest-cov>=4.1.0; extra == 'dev'
Requires-Dist: pytest>=7.4.0; extra == 'dev'
Requires-Dist: ruff>=0.1.0; extra == 'dev'
Provides-Extra: docs
Requires-Dist: pypdf>=4.0.0; extra == 'docs'
Requires-Dist: python-docx>=1.1.0; extra == 'docs'
Requires-Dist: python-pptx>=0.6.21; extra == 'docs'
